{
  "publicPath": "/_nuxt/",
  "all": [
    "../server/index.spa.html",
    "../server/index.ssr.html",
    "0bf3b271082a0a57e077.js",
    "0ed6a742dc3f4aca3706.css",
    "2341b125459a985f8700.js",
    "3fbe97a97c469046d7ef.js",
    "4068d08e9b9cd6e29013.js",
    "40c3e222e43c40ee232d.css",
    "46bbeff3e6ead8265e40.js",
    "4df168fc6a5a94e5d793.js",
    "58a945afa885a7b4ea53.js",
    "6b1e03e0f823afd9b9ae.js",
    "75937ad1374fa78a5329.js",
    "767912f449b8eb15f72a.css",
    "8929f0e31c46559fe663.js",
    "8b727ce2d685c880fb9e.css",
    "8d43119fb51d43e81e3d.css",
    "930a99fc85a541bf70ba.js",
    "LICENSES",
    "ab9ea5b067bda94cf802.css",
    "b289dd79877e4f7ecd61.css",
    "b40e6440056ba533bdbf.js",
    "be1a3c97bc102c113a8c.js",
    "de241149ef5e1730281d.css",
    "e382d33d41a298757695.css",
    "e50351d693900d0b8c3c.css",
    "f9deb72addf792d4a69c.js"
  ],
  "initial": [
    "be1a3c97bc102c113a8c.js",
    "4068d08e9b9cd6e29013.js",
    "b289dd79877e4f7ecd61.css",
    "58a945afa885a7b4ea53.js",
    "0ed6a742dc3f4aca3706.css",
    "930a99fc85a541bf70ba.js"
  ],
  "async": [
    "0bf3b271082a0a57e077.js",
    "2341b125459a985f8700.js",
    "3fbe97a97c469046d7ef.js",
    "40c3e222e43c40ee232d.css",
    "46bbeff3e6ead8265e40.js",
    "4df168fc6a5a94e5d793.js",
    "6b1e03e0f823afd9b9ae.js",
    "75937ad1374fa78a5329.js",
    "767912f449b8eb15f72a.css",
    "8929f0e31c46559fe663.js",
    "8b727ce2d685c880fb9e.css",
    "8d43119fb51d43e81e3d.css",
    "ab9ea5b067bda94cf802.css",
    "b40e6440056ba533bdbf.js",
    "de241149ef5e1730281d.css",
    "e382d33d41a298757695.css",
    "e50351d693900d0b8c3c.css",
    "f9deb72addf792d4a69c.js"
  ],
  "modules": {
    "12318024": [
      16,
      26
    ],
    "13359457": [
      6
    ],
    "13935984": [
      6
    ],
    "14756469": [
      6
    ],
    "16092851": [
      20,
      10
    ],
    "19688292": [
      6
    ],
    "20840208": [
      25,
      21
    ],
    "25065951": [
      24,
      2
    ],
    "29452702": [
      20,
      10
    ],
    "35793202": [
      14
    ],
    "36546841": [
      20,
      10
    ],
    "36931140": [
      6
    ],
    "44845197": [
      20,
      10
    ],
    "45741967": [
      20,
      10
    ],
    "46340792": [
      19,
      4
    ],
    "48169034": [
      20,
      10
    ],
    "52706954": [
      25,
      21
    ],
    "58692832": [
      6
    ],
    "69292039": [
      20,
      10
    ],
    "70824087": [
      24,
      2
    ],
    "73227767": [
      6
    ],
    "79140764": [
      20,
      10
    ],
    "79541880": [
      6
    ],
    "85622650": [
      3,
      17
    ],
    "97387398": [
      6
    ],
    "667a59c8": [
      6
    ],
    "65ce4eb5": [
      20,
      10
    ],
    "8d291116": [
      6
    ],
    "519eaaae": [
      6
    ],
    "01f2d284": [
      3,
      17
    ],
    "2a2c47d6": [
      20,
      10
    ],
    "2b93f2ba": [
      20,
      10
    ],
    "40ae9fd9": [
      6
    ],
    "e7c0323c": [
      20,
      10
    ],
    "0c8d239a": [
      6
    ],
    "628908bb": [
      6
    ],
    "6156792d": [
      6
    ],
    "6a29b3fe": [
      6
    ],
    "0e001a16": [
      6
    ],
    "58c3d4a7": [
      6
    ],
    "5aedd1e2": [
      6
    ],
    "c3a0a1f2": [
      6
    ],
    "119c1b08": [
      6
    ],
    "6e1dafde": [
      20,
      10
    ],
    "d78d64d0": [
      6
    ],
    "777a7eb8": [
      20,
      10
    ],
    "31c21253": [
      6
    ],
    "1185b0f6": [
      6
    ],
    "5951b707": [
      6
    ],
    "562cd3e0": [
      6
    ],
    "42b1aed9": [
      6
    ],
    "3767f916": [
      6
    ],
    "f4f08546": [
      6
    ],
    "66e07971": [
      6
    ],
    "119cdc14": [
      6
    ],
    "17b33fd6": [
      6
    ],
    "422ef14a": [
      20,
      10
    ],
    "34a77153": [
      6
    ],
    "4a8627f4": [
      6
    ],
    "3ba87a66": [
      6
    ],
    "22e439ee": [
      6
    ],
    "46233b62": [
      6
    ],
    "0790656c": [
      6
    ],
    "0d6a5c58": [
      6
    ],
    "4ca05d66": [
      6
    ],
    "038fd7ce": [
      6
    ],
    "565d6107": [
      6
    ],
    "0f8e70b9": [
      6
    ],
    "5aac1a10": [
      6
    ],
    "761e4a46": [
      6
    ],
    "541baf22": [
      6
    ],
    "4634d1b3": [
      20,
      10
    ],
    "735d334f": [
      20,
      10
    ],
    "154309fe": [
      20,
      10
    ],
    "9a5b7fbc": [
      20,
      10
    ],
    "9e27f324": [
      6
    ],
    "4e80602c": [
      6
    ],
    "1c095120": [
      6
    ],
    "29d61a78": [
      6
    ],
    "7f565fc4": [
      6
    ],
    "672bcade": [
      6
    ],
    "980e154c": [
      6
    ],
    "71925b57": [
      20,
      10
    ],
    "0e3f62e4": [
      6
    ],
    "58f87a19": [
      6
    ],
    "05c67ce4": [
      6
    ],
    "7fe2dd72": [
      6
    ],
    "6dd4548d": [
      6
    ],
    "57f42924": [
      6
    ],
    "7f195076": [
      6
    ],
    "57b2183d": [
      6
    ],
    "91bfddd2": [
      6
    ],
    "b93fce52": [
      20,
      10
    ],
    "3d6616c8": [
      20,
      10
    ],
    "4bab0206": [
      3,
      17
    ],
    "b5394414": [
      3,
      17
    ],
    "17c4fec4": [
      3,
      17
    ],
    "33b19cbf": [
      3,
      17
    ],
    "6c3db333": [
      3,
      17
    ],
    "0cbb6d24": [
      3,
      17
    ],
    "39cf808e": [
      3,
      17
    ],
    "7fc8f18b": [
      3,
      17
    ],
    "a6cdd2fe": [
      3,
      17
    ],
    "959b6e4e": [
      3,
      17
    ],
    "3ea03544": [
      3,
      17
    ],
    "4da11d0b": [
      3,
      17
    ],
    "6e8f6120": [
      3,
      17
    ],
    "b398851e": [
      3,
      17
    ],
    "5c1b1dbe": [
      3,
      17
    ],
    "77db50b8": [
      3,
      17
    ],
    "3b37385c": [
      3,
      17
    ],
    "6108a631": [
      3,
      17
    ],
    "7218042c": [
      3,
      17
    ],
    "2d00617c": [
      3,
      17
    ],
    "0f936c3e": [
      3,
      17
    ],
    "d0dcd196": [
      3,
      17
    ],
    "4e198979": [
      3,
      17
    ],
    "549a0654": [
      3,
      17
    ],
    "df4066ea": [
      3,
      17
    ],
    "2a03510f": [
      3,
      17
    ],
    "71cb4746": [
      3,
      17
    ],
    "27cc1ef4": [
      3,
      17
    ],
    "6d39ddc5": [
      3,
      17
    ],
    "62b7d5f0": [
      3,
      17
    ],
    "5c33b0a9": [
      3,
      17
    ],
    "aa62c17a": [
      3,
      17
    ],
    "6698c51c": [
      3,
      17
    ],
    "d36b1dfa": [
      3,
      17
    ],
    "40cbe5fa": [
      3,
      17
    ],
    "0e2d802d": [
      3,
      17
    ],
    "b16da32e": [
      3,
      17
    ],
    "51af1b72": [
      3,
      17
    ],
    "622bce72": [
      6
    ],
    "a30345cc": [
      6
    ],
    "0ca6fa49": [
      6
    ],
    "0a23c5c6": [
      6
    ],
    "2e44680c": [
      6
    ],
    "179c75f8": [
      6
    ],
    "94fcad34": [
      6
    ],
    "4e6d4aae": [
      6
    ],
    "bb5000aa": [
      20,
      10
    ],
    "f7ebdaa8": [
      6
    ],
    "26201a32": [
      6
    ],
    "59aeba64": [
      6
    ],
    "5bbb6a21": [
      6
    ],
    "5b279a0a": [
      6
    ],
    "d2c59e10": [
      6
    ],
    "b74328d4": [
      6
    ],
    "25fa5cc2": [
      6
    ],
    "a597b284": [
      20,
      10
    ],
    "318d905e": [
      6
    ],
    "a2f763f0": [
      6
    ],
    "1daa38a9": [
      6
    ],
    "7c8fdbff": [
      6
    ],
    "7c4137cc": [
      6
    ],
    "321d0546": [
      6
    ],
    "ff34a056": [
      6
    ],
    "0a141703": [
      6
    ],
    "ee29c204": [
      6
    ],
    "1f8d376f": [
      6
    ],
    "00ea0e28": [
      6
    ],
    "293dff06": [
      6
    ],
    "7063b0d0": [
      6
    ],
    "49f587e3": [
      20,
      10
    ],
    "3b5da39c": [
      20,
      10
    ],
    "56de9341": [
      6
    ],
    "48ae7c00": [
      20,
      10
    ],
    "2e07cfc0": [
      6
    ],
    "494dfc42": [
      20,
      10
    ],
    "0f8be8b7": [
      6
    ],
    "0173e16b": [
      6
    ],
    "caba0594": [
      6
    ],
    "41d7c49d": [
      6
    ],
    "4a92bbc8": [
      6
    ],
    "db4e2c7c": [
      6
    ],
    "07ccb73e": [
      6
    ],
    "a3d55f3c": [
      6
    ],
    "72085c5a": [
      6
    ],
    "a8210e2e": [
      6
    ],
    "2e356082": [
      6
    ],
    "0fd39b18": [
      6
    ],
    "6a183150": [
      6
    ],
    "49e53e73": [
      6
    ],
    "512142a6": [
      6
    ],
    "1ec4dcb2": [
      20,
      10
    ],
    "38fdef58": [
      20,
      10
    ],
    "4477908c": [
      20,
      10
    ],
    "4b623a98": [
      20,
      10
    ],
    "419fce9b": [
      20,
      10
    ],
    "e92ff9a0": [
      3,
      17
    ],
    "29a2c6f7": [
      6
    ],
    "eac80fde": [
      6
    ],
    "0453953d": [
      6
    ],
    "3bc8b67c": [
      6
    ],
    "7266faba": [
      6
    ],
    "28a39d8a": [
      6
    ],
    "36be1fc3": [
      6
    ],
    "5bef996d": [
      6
    ],
    "750b05fa": [
      6
    ],
    "3d88207c": [
      6
    ],
    "575096e4": [
      6
    ],
    "b561ce80": [
      20,
      10
    ],
    "10223f4b": [
      6
    ],
    "071ec3e4": [
      6
    ],
    "a54bbec4": [
      6
    ],
    "4da9e188": [
      6
    ],
    "429297ae": [
      20,
      10
    ],
    "fc4ea0fa": [
      6
    ],
    "05e83178": [
      6
    ],
    "270e6a3e": [
      6
    ],
    "508c0f2d": [
      6
    ],
    "d489726c": [
      6
    ],
    "5089c952": [
      6
    ],
    "04616bdf": [
      6
    ],
    "1744fdee": [
      6
    ],
    "795c1baa": [
      6
    ],
    "dd6a426c": [
      6
    ],
    "61dac172": [
      6
    ],
    "cbac0e92": [
      6
    ],
    "e7251310": [
      6
    ],
    "a554d630": [
      6
    ],
    "251cd5fe": [
      6
    ],
    "7fcd9aea": [
      6
    ],
    "f3b9ee5e": [
      20,
      10
    ],
    "78ebc2f7": [
      20,
      10
    ],
    "761d9e58": [
      3,
      17
    ],
    "1348e2c2": [
      3,
      17
    ],
    "7a57509a": [
      20,
      10
    ],
    "2ee0ed66": [
      20,
      10
    ],
    "7c95a215": [
      20,
      10
    ],
    "c73c767a": [
      3,
      17
    ],
    "f1499e24": [
      6
    ],
    "232edb2a": [
      20,
      10
    ],
    "30c4ae01": [
      3,
      17
    ],
    "1b256e6d": [
      6
    ],
    "7218cceb": [
      6
    ],
    "5fc5792d": [
      6
    ],
    "062fa7aa": [
      6
    ],
    "9b4ca77e": [
      6
    ],
    "dc4fe5da": [
      6
    ],
    "4b604531": [
      6
    ],
    "b46e15a6": [
      6
    ],
    "50853d9c": [
      6
    ],
    "5b354db2": [
      6
    ],
    "087af991": [
      6
    ],
    "f4d8bf7c": [
      6
    ],
    "62af5ee5": [
      6
    ],
    "538ac48c": [
      6
    ],
    "1bc19ffd": [
      6
    ],
    "161cddd3": [
      6
    ],
    "bed09d62": [
      20,
      10
    ],
    "9ff7491a": [
      6
    ],
    "4a7c5736": [
      6
    ],
    "0fe0a979": [
      6
    ],
    "a547330e": [
      6
    ],
    "050d71a3": [
      6
    ],
    "5ad4775b": [
      6
    ],
    "c097c7bc": [
      6
    ],
    "654b50dd": [
      6
    ],
    "52b3815f": [
      6
    ],
    "08f66a89": [
      6
    ],
    "436cfd96": [
      20,
      10
    ],
    "63f0bc61": [
      20,
      10
    ],
    "723f5d52": [
      20,
      10
    ],
    "7f429a66": [
      20,
      10
    ],
    "53b5cd61": [
      20,
      10
    ],
    "10356f97": [
      20,
      10
    ],
    "00abc755": [
      20,
      10
    ],
    "a9f60a12": [
      3,
      17
    ],
    "3753170d": [
      3,
      17
    ],
    "b0ee7bd8": [
      20,
      10
    ],
    "71426b10": [
      6
    ],
    "0a7881c3": [
      20,
      10
    ],
    "1999e786": [
      20,
      10
    ],
    "6ce3acea": [
      20,
      10
    ],
    "8f58b8c8": [
      20,
      10
    ],
    "2b579d2a": [
      20,
      10
    ],
    "6ccfe041": [
      20,
      10
    ],
    "4887f8ff": [
      20,
      10
    ],
    "e7e55b1c": [
      20,
      10
    ],
    "9e656290": [
      20,
      10
    ],
    "7d642546": [
      20,
      10
    ],
    "7ace0d97": [
      20,
      10
    ],
    "6e723e60": [
      20,
      10
    ],
    "d98fe308": [
      20,
      10
    ],
    "9e2d2b9a": [
      20,
      10
    ],
    "1c5cc665": [
      20,
      10
    ],
    "530689c9": [
      20,
      10
    ],
    "0de49f5c": [
      20,
      10
    ],
    "52a28825": [
      20,
      10
    ],
    "01b054d5": [
      20,
      10
    ],
    "ea11baa4": [
      20,
      10
    ],
    "7049a960": [
      20,
      10
    ],
    "4ff9bbe6": [
      20,
      10
    ],
    "418fe72c": [
      20,
      10
    ],
    "205e0b43": [
      20,
      10
    ],
    "6c5ecdd4": [
      20,
      10
    ],
    "0481a7a5": [
      20,
      10
    ],
    "d3643db4": [
      20,
      10
    ],
    "5508eb62": [
      20,
      10
    ],
    "7edaf056": [
      6
    ],
    "2a11e01f": [
      20,
      10
    ],
    "58fc209c": [
      20,
      10
    ],
    "292d8f52": [
      6
    ],
    "20a744ba": [
      6
    ],
    "cb252d70": [
      20,
      10
    ],
    "3ebc23c2": [
      6
    ],
    "9cdf4ff4": [
      6
    ],
    "7ffdd2d5": [
      20,
      10
    ],
    "7cadb5df": [
      20,
      10
    ],
    "54b65dbf": [
      6
    ],
    "543047b3": [
      6
    ],
    "a349459e": [
      6
    ],
    "4ed28240": [
      6
    ],
    "0603ebc4": [
      6
    ],
    "759e1ee9": [
      6
    ],
    "38dba588": [
      6
    ],
    "1d6b16bd": [
      6
    ],
    "46d70373": [
      6
    ],
    "c073b852": [
      6
    ],
    "560f7a4d": [
      6
    ],
    "81c912e4": [
      6
    ],
    "c0e77b12": [
      6
    ],
    "3c286714": [
      6
    ],
    "539c233f": [
      6
    ],
    "c35edf96": [
      6
    ],
    "034f2ffe": [
      6
    ],
    "781de2a3": [
      6
    ],
    "20f27251": [
      6
    ],
    "4629af8c": [
      6
    ],
    "2ccbc815": [
      6
    ],
    "27062bc2": [
      6
    ],
    "3d1e1389": [
      6
    ],
    "6198a9a5": [
      6
    ],
    "450197f6": [
      6
    ],
    "3f773144": [
      6
    ],
    "e979f5ce": [
      6
    ],
    "288ce474": [
      6
    ],
    "3ddd3af4": [
      6
    ],
    "00ee1e6f": [
      6
    ],
    "79079eea": [
      20,
      10
    ],
    "837e3bdc": [
      6
    ],
    "f18b9b36": [
      6
    ],
    "41bb3b75": [
      6
    ],
    "6105dd14": [
      6
    ],
    "2254312c": [
      6
    ],
    "4e7cf41d": [
      6
    ],
    "4cfe6a44": [
      6
    ],
    "0651c50c": [
      6
    ],
    "460824ff": [
      6
    ],
    "37d0261a": [
      6
    ],
    "2c566646": [
      6
    ],
    "29cfa3e8": [
      6
    ],
    "7ae1fcc3": [
      6
    ],
    "772f6569": [
      6
    ],
    "c9360d04": [
      6
    ],
    "9c1de48a": [
      6
    ],
    "722aa376": [
      20,
      10
    ],
    "08822814": [
      6
    ],
    "7209f5e3": [
      6
    ],
    "8ddd4870": [
      20,
      10
    ],
    "09f393d4": [
      20,
      10
    ],
    "0a006245": [
      20,
      10
    ],
    "77b83557": [
      20,
      10
    ],
    "78a44aee": [
      20,
      10
    ],
    "4497533d": [
      6
    ],
    "f37a214e": [
      6
    ],
    "d749305e": [
      6
    ],
    "2d19a112": [
      6
    ],
    "da877666": [
      6
    ],
    "4d372a28": [
      6
    ],
    "05bba83a": [
      6
    ],
    "2ec6558a": [
      6
    ],
    "08257b9e": [
      20,
      10
    ],
    "49ec3a54": [
      6
    ],
    "83ad5f26": [
      20,
      10
    ],
    "d3528f52": [
      20,
      10
    ],
    "47ffa78d": [
      20,
      10
    ],
    "3b79f99e": [
      20,
      10
    ],
    "6e64f0b9": [
      3,
      17
    ],
    "5cb87133": [
      3,
      17
    ],
    "af992196": [
      6
    ],
    "262a24fa": [
      20,
      10
    ],
    "dec89ade": [
      6
    ],
    "222cbdbf": [
      6
    ],
    "09ddd823": [
      6
    ],
    "50fb3f99": [
      6
    ],
    "1bebcdda": [
      6
    ],
    "614d7d6f": [
      6
    ],
    "f7b5a2dc": [
      3,
      17
    ],
    "29d99a34": [
      3,
      17
    ],
    "5c53bdda": [
      6
    ],
    "0caf3223": [
      6
    ],
    "8e967df4": [
      6
    ],
    "4c9c8810": [
      6
    ],
    "399acbdc": [
      6
    ],
    "fcabbde2": [
      6
    ],
    "87e37704": [
      6
    ],
    "26b7391f": [
      6
    ],
    "51de3195": [
      6
    ],
    "f2724d20": [
      6
    ],
    "4facc5be": [
      6
    ],
    "f39b0252": [
      6
    ],
    "95740f76": [
      6
    ],
    "cb23d698": [
      6
    ],
    "8e73d61c": [
      6
    ],
    "1d4cce31": [
      6
    ],
    "40beb266": [
      6
    ],
    "788cba90": [
      6
    ],
    "62f0b95d": [
      6
    ],
    "c6a355f6": [
      6
    ],
    "1c685025": [
      6
    ],
    "34f80d06": [
      6
    ],
    "0260b02f": [
      6
    ],
    "6734fac8": [
      6
    ],
    "661d14b4": [
      3,
      17
    ],
    "e048f930": [
      6
    ],
    "58ab6dec": [
      6
    ],
    "41408e86": [
      6
    ],
    "5231cd0b": [
      6
    ],
    "66c6472a": [
      6
    ],
    "e999293a": [
      6
    ],
    "2f6872c3": [
      6
    ],
    "7416bf18": [
      6
    ],
    "0d0af8fe": [
      6
    ],
    "f1e0978c": [
      6
    ],
    "0addda85": [
      6
    ],
    "458ba89a": [
      6
    ],
    "31117d17": [
      6
    ],
    "0907488e": [
      6
    ],
    "82b4c7f4": [
      6
    ],
    "14989a5a": [
      6
    ],
    "55c94fea": [
      20,
      10
    ],
    "a8df8c78": [
      20,
      10
    ],
    "1c9f8832": [
      20,
      10
    ],
    "21baed3a": [
      3,
      17
    ],
    "c8ca4a5a": [
      3,
      17
    ],
    "362c7c0d": [
      6
    ],
    "53a15fac": [
      6
    ],
    "290fa5bc": [
      6
    ],
    "270fdb56": [
      6
    ],
    "02e672e2": [
      6
    ],
    "7c3a2f8c": [
      6
    ],
    "554db82e": [
      6
    ],
    "d402432e": [
      6
    ],
    "727ea620": [
      6
    ],
    "48b083fe": [
      6
    ],
    "538c2244": [
      6
    ],
    "4932590c": [
      6
    ],
    "e1f7474c": [
      3,
      17
    ],
    "6bc67cc4": [
      3,
      17
    ],
    "d39f5be0": [
      20,
      10
    ],
    "72ecf4b5": [
      3,
      17
    ],
    "529cd90e": [
      6
    ],
    "7f504841": [
      6
    ],
    "d7eb095c": [
      6
    ],
    "110bb043": [
      6
    ],
    "07b5c61e": [
      6
    ],
    "01ebd46c": [
      6
    ],
    "769bde4a": [
      6
    ],
    "a2a2ee3e": [
      6
    ],
    "162868a4": [
      6
    ],
    "715498b5": [
      6
    ],
    "37425eb4": [
      6
    ],
    "7c178d7a": [
      6
    ],
    "58dade1f": [
      20,
      10
    ],
    "16785f5e": [
      20,
      10
    ],
    "39507f5e": [
      20,
      10
    ],
    "69b30a6b": [
      6
    ],
    "22c8296e": [
      6
    ],
    "5f11540b": [
      6
    ],
    "68a47adb": [
      6
    ],
    "262b74d6": [
      6
    ],
    "14f974e5": [
      6
    ],
    "a7dd5b5e": [
      20,
      10
    ],
    "0095931b": [
      20,
      10
    ],
    "f12afb8a": [
      6
    ],
    "b813f606": [
      6
    ],
    "c6ff30de": [
      20,
      10
    ],
    "15addeb1": [
      20,
      10
    ],
    "7ac0770a": [
      6
    ],
    "2bfda5eb": [
      20,
      10
    ],
    "59dd92de": [
      20,
      10
    ],
    "60ee7607": [
      20,
      10
    ],
    "ebf77d98": [
      20,
      10
    ],
    "6f7da2dc": [
      20,
      10
    ],
    "8e4750f6": [
      20,
      10
    ],
    "392f7d71": [
      20,
      10
    ],
    "ff2aaaf6": [
      20,
      10
    ],
    "4921b859": [
      3,
      17
    ],
    "0bc580de": [
      20,
      10
    ],
    "598170b7": [
      20,
      10
    ],
    "b52daade": [
      20,
      10
    ],
    "a278d138": [
      3,
      17
    ],
    "a7f641c2": [
      6
    ],
    "de43f878": [
      6
    ],
    "3139dbab": [
      20,
      10
    ],
    "5d6c1246": [
      6
    ],
    "2d87872f": [
      6
    ],
    "fc04a58c": [
      6
    ],
    "156045f0": [
      6
    ],
    "4017e5be": [
      6
    ],
    "24c23652": [
      6
    ],
    "2fcbce82": [
      6
    ],
    "09f5efde": [
      6
    ],
    "02c44d2f": [
      6
    ],
    "50ae6c8f": [
      6
    ],
    "9f8abc9c": [
      6
    ],
    "a39e41f4": [
      6
    ],
    "64b96f5e": [
      6
    ],
    "149324e3": [
      6
    ],
    "9b4ee0f6": [
      6
    ],
    "61d544ba": [
      6
    ],
    "03dbd587": [
      6
    ],
    "0ef1a865": [
      20,
      10
    ],
    "10969bd0": [
      20,
      10
    ],
    "1dbe2e85": [
      20,
      10
    ],
    "402316c0": [
      20,
      10
    ],
    "267b4956": [
      20,
      10
    ],
    "79592c0f": [
      20,
      10
    ],
    "2fd331c3": [
      6
    ],
    "a32440c6": [
      6
    ],
    "5a39db76": [
      20,
      10
    ],
    "3574ee3d": [
      20,
      10
    ],
    "fc892336": [
      20,
      10
    ],
    "0a8da1ff": [
      15,
      12
    ],
    "9c52533c": [
      24,
      2
    ],
    "4eeb97ae": [
      24,
      2
    ],
    "346adcb7": [
      20,
      10
    ],
    "7bebae41": [
      20,
      10
    ],
    "6366bab1": [
      20,
      10
    ],
    "6c8c226a": [
      20,
      10
    ],
    "a79c3e70": [
      20,
      10
    ],
    "3c0bbb92": [
      20,
      10
    ],
    "ccb3e052": [
      20,
      10
    ],
    "160614d2": [
      20,
      10
    ],
    "176d74d2": [
      20,
      10
    ],
    "0e39d936": [
      20,
      10
    ],
    "252f8b86": [
      20,
      10
    ],
    "1ac05a4c": [
      20,
      10
    ],
    "656790ca": [
      20,
      10
    ],
    "10bb92ef": [
      20,
      10
    ],
    "7f26c597": [
      23,
      8
    ],
    "2d3522df": [
      23,
      8
    ],
    "729f4b8e": [
      23,
      8
    ],
    "08680637": [
      23,
      8
    ],
    "753bd8db": [
      19,
      4
    ],
    "219bac40": [
      24,
      2
    ],
    "3dbff454": [
      15,
      12
    ],
    "22fdc361": [
      16,
      26
    ],
    "5c9a6e44": [
      7,
      9
    ],
    "01aed7d8": [
      23,
      8
    ],
    "ecc7c13e": [
      23,
      8
    ],
    "c6974fde": [
      23,
      8
    ],
    "b47e1384": [
      23,
      8
    ],
    "54bd2f1e": [
      23,
      8
    ],
    "72329f3a": [
      24,
      2
    ],
    "7a1d257d": [
      24,
      2
    ],
    "101c1ffe": [
      24,
      2
    ],
    "781e80fd": [
      24,
      2
    ],
    "66fb9361": [
      24,
      2
    ],
    "7f5ca2de": [
      23,
      8
    ],
    "68fcb337": [
      23,
      8
    ],
    "b5f8dc3e": [
      23,
      8
    ],
    "3c5c06f1": [
      23,
      8
    ],
    "261412b2": [
      23,
      8
    ],
    "400afe77": [
      23,
      8
    ],
    "332f8a9e": [
      13,
      11
    ],
    "97917a9e": [
      23,
      8
    ],
    "00dfbdf1": [
      23,
      8
    ],
    "0b7fa7aa": [
      23,
      8
    ],
    "2cda4331": [
      23,
      8
    ],
    "305a52ab": [
      23,
      8
    ],
    "7888eb4f": [
      23,
      8
    ],
    "dfdd300e": [
      24,
      2
    ],
    "75e7f3bd": [
      24,
      2
    ],
    "1eee6f5d": [
      24,
      2
    ],
    "f7ae6840": [
      24,
      2
    ],
    "19d2b29e": [
      24,
      2
    ],
    "3264f597": [
      24,
      2
    ],
    "7bd943c2": [
      24,
      2
    ],
    "646d0ff8": [
      24,
      2
    ],
    "5f24d085": [
      19,
      4
    ],
    "1cbc2973": [
      24,
      2
    ],
    "2edc74b1": [
      24,
      2
    ],
    "774ee945": [
      24,
      2
    ],
    "33defd2c": [
      24,
      2
    ],
    "159f755e": [
      24,
      2
    ],
    "9db0e1ea": [
      24,
      2
    ],
    "f7814daa": [
      24,
      2
    ],
    "41fcf811": [
      24,
      2
    ],
    "83578ac4": [
      25,
      21
    ],
    "2091b047": [
      15,
      12
    ],
    "789b9767": [
      15,
      12
    ],
    "09f333ba": [
      15,
      12
    ],
    "0ce6bb0b": [
      16,
      26
    ],
    "07ced0dc": [
      7,
      9
    ],
    "982de186": [
      7,
      9
    ],
    "5fb312f0": [
      7,
      9
    ],
    "3071bf39": [
      7,
      9
    ],
    "224e4dfe": [
      15,
      12
    ],
    "1cce672e": [
      15,
      12
    ],
    "3d53e8fe": [
      23,
      8
    ],
    "c15b81d6": [
      23,
      8
    ],
    "46b6e724": [
      15,
      12
    ],
    "60d0e6c8": [
      13,
      11
    ],
    "213b9bd5": [
      13,
      11
    ],
    "05e4cdc8": [
      13,
      11
    ],
    "182d5e6e": [
      13,
      11
    ],
    "29ecce8a": [
      13,
      11
    ],
    "a277773c": [
      13,
      11
    ],
    "889a5f92": [
      13,
      11
    ],
    "8f81e15e": [
      24,
      2
    ],
    "ebdee65a": [
      24,
      2
    ],
    "0bd60107": [
      24,
      2
    ],
    "76751c0f": [
      24,
      2
    ],
    "6ebaf7b1": [
      24,
      2
    ],
    "2587a524": [
      24,
      2
    ],
    "1e176597": [
      24,
      2
    ],
    "1a460c47": [
      7,
      9
    ],
    "7fa14714": [
      7,
      9
    ],
    "14142a33": [
      7,
      9
    ],
    "fca3c924": [
      7,
      9
    ],
    "6b0e1b4e": [
      7,
      9
    ],
    "d759f502": [
      7,
      9
    ],
    "ea0c8824": [
      19,
      4
    ],
    "e46fd6ba": [
      19,
      4
    ],
    "61c9b96c": [
      19,
      4
    ],
    "3973e2fd": [
      19,
      4
    ],
    "5fba505e": [
      25,
      21
    ],
    "0f17d31c": [
      25,
      21
    ],
    "6f342b3c": [
      25,
      21
    ],
    "6e7aea0c": [
      25,
      21
    ],
    "4c844636": [
      14
    ],
    "56175fb6": [
      14
    ],
    "6d31c664": [
      14
    ],
    "3fcb27ec": [
      14
    ],
    "405ebb44": [
      5
    ],
    "5489d73c": [
      5
    ],
    "c260d568": [
      5
    ],
    "32fca622": [
      5
    ],
    "99eeba34": [
      5
    ],
    "1229131c": [
      16,
      26
    ],
    "6caaf8e6": [
      16,
      26
    ],
    "2dc731fe": [
      16,
      26
    ],
    "755651e7": [
      16,
      26
    ],
    "558723b9": [
      24,
      2
    ],
    "1b2d9cbd": [
      24,
      2
    ],
    "23c5d9ea": [
      24,
      2
    ],
    "ff6ed092": [
      24,
      2
    ],
    "8fe905e6": [
      15,
      12
    ],
    "3b7b43ec": [
      15,
      12
    ],
    "bae0ab64": [
      15,
      12
    ],
    "160363ad": [
      15,
      12
    ],
    "7c08ce0b": [
      24,
      2
    ],
    "0187eb5a": [
      24,
      2
    ],
    "0a64ea24": [
      24,
      2
    ],
    "4a5258db": [
      15,
      12
    ],
    "4ae02356": [
      15,
      12
    ],
    "758855d6": [
      3,
      17
    ],
    "1c3ef387": [
      3,
      17
    ],
    "2a24150c": [
      3,
      17
    ],
    "9af39972": [
      7,
      9
    ],
    "1952a6ca": [
      16,
      26
    ],
    "6b90bc44": [
      19,
      4
    ],
    "10ea0182": [
      25,
      21
    ],
    "281f4167": [
      20,
      10
    ],
    "40999e32": [
      20,
      10
    ],
    "43afe087": [
      20,
      10
    ],
    "31e21332": [
      20,
      10
    ],
    "5feef2c9": [
      24,
      2
    ],
    "14b70267": [
      20,
      10
    ],
    "05f82b87": [
      13,
      11
    ],
    "0f0a550d": [
      20,
      10
    ],
    "2e2d2f44": [
      20,
      10
    ],
    "68dbe6b2": [
      20,
      10
    ],
    "4bd957b2": [
      20,
      10
    ],
    "16775a5d": [
      20,
      10
    ],
    "2930e008": [
      20,
      10
    ],
    "6591eaec": [
      20,
      10
    ],
    "35bff3ef": [
      20,
      10
    ],
    "174b4f3e": [
      24,
      2
    ],
    "c05824e2": [
      7,
      9
    ],
    "53cad6c6": [
      15,
      12
    ],
    "87776e32": [
      23,
      8
    ],
    "3029ccb6": [
      23,
      8
    ],
    "36699c27": [
      20,
      10
    ],
    "58bf6e47": [
      20,
      10
    ],
    "5a38e727": [
      20,
      10
    ],
    "3e392f79": [
      15,
      12
    ],
    "50a12069": [
      20,
      10
    ],
    "3f945115": [
      20,
      10
    ],
    "f3c221fe": [
      24,
      2
    ],
    "343991fe": [
      23,
      8
    ],
    "6e800f07": [
      23,
      8
    ],
    "2b186987": [
      23,
      8
    ],
    "77c0e4c7": [
      23,
      8
    ],
    "35f38edb": [
      20,
      10
    ],
    "7beca671": [
      20,
      10
    ],
    "181aaa86": [
      15,
      12
    ],
    "5ac324d4": [
      3,
      17
    ],
    "c7e4b116": [
      20,
      10
    ],
    "618ce8e7": [
      24,
      2
    ],
    "69a25a81": [
      23,
      8
    ]
  },
  "assetsMapping": {
    "0bf3b271082a0a57e077.js": "4fae17f4",
    "2341b125459a985f8700.js": "35a02e5e",
    "3fbe97a97c469046d7ef.js": "2a130dde",
    "4068d08e9b9cd6e29013.js": "0859c165",
    "46bbeff3e6ead8265e40.js": "118e4b12",
    "4df168fc6a5a94e5d793.js": "4939a2aa",
    "58a945afa885a7b4ea53.js": "7ea1d828",
    "6b1e03e0f823afd9b9ae.js": "8444d1d6",
    "75937ad1374fa78a5329.js": "13b851e8",
    "8929f0e31c46559fe663.js": "f6b7b64e",
    "930a99fc85a541bf70ba.js": "1a3ae26b",
    "b40e6440056ba533bdbf.js": "1c72762b",
    "be1a3c97bc102c113a8c.js": "6fca0322",
    "f9deb72addf792d4a69c.js": "b3d3f202"
  }
}